tidy3d_extras.libs/libgomp-a34b3233.so.1.0.0
tidy3d_extras.libs/libhdf5-a5005457.so.310.5.1
tidy3d_extras-2.10.2.dist-info/WHEEL
tidy3d_extras-2.10.2.dist-info/METADATA
tidy3d_extras-2.10.2.dist-info/RECORD
tidy3d_extras-2.10.2.dist-info/licenses/LICENSE
tidy3d_extras/utils.py
tidy3d_extras/mode.py
tidy3d_extras/colocation.py
tidy3d_extras/extension.cpython-39-x86_64-linux-gnu.so
tidy3d_extras/subpixel.py
tidy3d_extras/__init__.py
tidy3d_extras/core/config.json
tidy3d_extras/core/simulation.py
tidy3d_extras/core/subgrid.py
tidy3d_extras/core/config.py
tidy3d_extras/core/custom_medium.py
