Metadata-Version: 2.2
Name: tidy3d-extras
Version: 2.10.2
Summary: tidy3d-extras is an optional plugin for Tidy3D providing addtional, more advanced local functionality.
Author-Email: "Flexcompute Inc." <support@flexcompute.com>
Project-URL: homepage, https://www.flexcompute.com/
Project-URL: documentation, https://docs.flexcompute.com/projects/tidy3d/
Requires-Python: >=3.9
Requires-Dist: numpy>=2.0
Requires-Dist: tidy3d==2.10.2
Requires-Dist: xarray>=2024.6
Provides-Extra: test
Requires-Dist: pytest>=7.2; extra == "test"
